MANIFEST.in
README.md
requirements.pip
setup.py
gachette/__init__.py
gachette/api.py
gachette/main.py
gachette/lib/__init__.py
gachette/lib/stack.py
gachette/lib/utils.py
gachette/lib/working_copy.py
gachette/templates/example.yml
la_gachette.egg-info/PKG-INFO
la_gachette.egg-info/SOURCES.txt
la_gachette.egg-info/dependency_links.txt
la_gachette.egg-info/entry_points.txt
la_gachette.egg-info/requires.txt
la_gachette.egg-info/top_level.txt