Metadata-Version: 1.1
Name: la-gachette
Version: 0.0.6
Summary: Module to handle working copy and build of project.
Home-page: UNKNOWN
Author: Arnaud Seilles
Author-email: arnaud.seilles@gmail.com
License: UNKNOWN
Platform: UNKNOWN
Classifier: Development Status :: 3 - Alpha
Classifier: Intended Audience :: Information Technology
Classifier: License :: OSI Approved :: GNU Affero General Public License v3
Classifier: Operating System :: POSIX :: Linux
Classifier: Programming Language :: Python :: 2.7
Classifier: Topic :: Software Development :: Build Tools
Classifier: Topic :: Software Development :: Libraries :: Python Modules
